nofnof_filler/.DS_Store
nofnof_filler/__init__.py
nofnof_filler/main.py
nofnof_filler/src/.DS_Store
nofnof_filler/src/__init__.py
nofnof_filler/src/mapping.py
nofnof_filler/src/noFillNoFuture.py
nofnof_filler/src/token.py
nofnof_filler-1.0.4.dist-info/WHEEL
nofnof_filler-1.0.4.dist-info/METADATA
nofnof_filler-1.0.4.dist-info/RECORD
